dj_database_url.py
dj_config_url.py
dj_config_url-0.1.1.dist-info/RECORD
dj_config_url-0.1.1.dist-info/METADATA
dj_config_url-0.1.1.dist-info/DESCRIPTION.rst
dj_config_url-0.1.1.dist-info/WHEEL
dj_config_url-0.1.1.dist-info/top_level.txt
dj_config_url-0.1.1.dist-info/metadata.json
